odoo/addons/account_payment_select_cost_account/README.rst
odoo/addons/account_payment_select_cost_account/__init__.py
odoo/addons/account_payment_select_cost_account/__manifest__.py
odoo/addons/account_payment_select_cost_account/i18n/account_payment_select_cost_account.pot
odoo/addons/account_payment_select_cost_account/i18n/pt.po
odoo/addons/account_payment_select_cost_account/models/__init__.py
odoo/addons/account_payment_select_cost_account/models/account_payment.py
odoo/addons/account_payment_select_cost_account/readme/CONTRIBUTORS.rst
odoo/addons/account_payment_select_cost_account/readme/CREDITS.rst
odoo/addons/account_payment_select_cost_account/readme/DESCRIPTION.rst
odoo/addons/account_payment_select_cost_account/readme/USAGE.rst
odoo/addons/account_payment_select_cost_account/static/description/icon.png
odoo/addons/account_payment_select_cost_account/static/description/index.html
odoo/addons/account_payment_select_cost_account/tests/__init__.py
odoo/addons/account_payment_select_cost_account/tests/test_account_payment_select_cost_account.py
odoo/addons/account_payment_select_cost_account/views/account_payment_view.xml
odoo12_addon_account_payment_select_cost_account-12.0.1.0.0.99.dev7.dist-info/METADATA
odoo12_addon_account_payment_select_cost_account-12.0.1.0.0.99.dev7.dist-info/WHEEL
odoo12_addon_account_payment_select_cost_account-12.0.1.0.0.99.dev7.dist-info/top_level.txt
odoo12_addon_account_payment_select_cost_account-12.0.1.0.0.99.dev7.dist-info/RECORD
